spikeble/__init__.py
spikeble/_utils.py
spikeble/spike.py
spikeble/_lib/cobs.py
spikeble/_lib/connection.py
spikeble/_lib/crc.py
spikeble/_lib/enumeration.py
spikeble/_lib/messages.py
spikeble/_lib/readme
spikeble/micropython/app/__init__.py
spikeble/micropython/app/bargraph.py
spikeble/micropython/app/display.py
spikeble/micropython/app/linegraph.py
spikeble/micropython/app/music.py
spikeble/micropython/app/sound.py
spikeble/micropython/color/__init__.py
spikeble/micropython/color_matrix/__init__.py
spikeble/micropython/color_sensor/__init__.py
spikeble/micropython/device/__init__.py
spikeble/micropython/distance_sensor/__init__.py
spikeble/micropython/force_sensor/__init__.py
spikeble/micropython/hub/__init__.py
spikeble/micropython/hub/button.py
spikeble/micropython/hub/light.py
spikeble/micropython/hub/light_matrix.py
spikeble/micropython/hub/motion_sensor.py
spikeble/micropython/hub/port.py
spikeble/micropython/hub/sound.py
spikeble/micropython/motor/__init__.py
spikeble/micropython/motor_pair/__init__.py
spikeble/micropython/orientation/__init__.py
spikeble/micropython/runloop/__init__.py
app/__init__.py
app/bargraph.py
app/display.py
app/linegraph.py
app/music.py
app/sound.py
color/__init__.py
color_matrix/__init__.py
color_sensor/__init__.py
device/__init__.py
distance_sensor/__init__.py
force_sensor/__init__.py
hub/__init__.py
hub/button.py
hub/light.py
hub/light_matrix.py
hub/motion_sensor.py
hub/port.py
hub/sound.py
motor/__init__.py
motor_pair/__init__.py
orientation/__init__.py
runloop/__init__.py
spikeble-0.1.dist-info/METADATA
spikeble-0.1.dist-info/WHEEL
spikeble-0.1.dist-info/licenses/LICENSE
spikeble-0.1.dist-info/RECORD
