Metadata-Version: 2.4
Name: spikeble
Version: 0.1
Summary: BLE interface for running Micropython on LEGO SPIKE devices
Project-URL: Homepage, https://github.com/MGross21/spikeble
Project-URL: Repository, https://github.com/MGross21/spikeble
Project-URL: Issues, https://github.com/MGross21/spikeble/issues
Author-email: Michael Gross <MGross21@users.noreply.github.com>
License: Copyright 2025 Michael Gross
License-File: LICENSE
Keywords: ble,bluetooth,lego,robotics,spike
Classifier: License :: OSI Approved :: MIT License
Classifier: Operating System :: OS Independent
Classifier: Programming Language :: Python :: 3
Classifier: Programming Language :: Python :: 3 :: Only
Classifier: Topic :: Software Development :: Libraries
Classifier: Topic :: System :: Hardware
Requires-Python: >=3.11
Requires-Dist: bleak>=1.0.0
